{
  "version": "0.1.0",
  "name": "blog",
  "dependencies": {
    "@emotion/react": {
      "version": "11.10.4",
      "resolved": "https://registry.npmjs.org/@emotion/react/-/react-11.10.4.tgz"
    },
    "@emotion/styled": {
      "version": "11.10.4",
      "resolved": "https://registry.npmjs.org/@emotion/styled/-/styled-11.10.4.tgz"
    },
    "@fontsource/dancing-script": {
      "version": "4.5.11",
      "resolved": "https://registry.npmjs.org/@fontsource/dancing-script/-/dancing-script-4.5.11.tgz"
    },
    "@fontsource/josefin-sans": {
      "version": "4.5.12",
      "resolved": "https://registry.npmjs.org/@fontsource/josefin-sans/-/josefin-sans-4.5.12.tgz"
    },
    "@fontsource/mouse-memoirs": {
      "version": "4.5.11",
      "resolved": "https://registry.npmjs.org/@fontsource/mouse-memoirs/-/mouse-memoirs-4.5.11.tgz"
    },
    "@fontsource/ms-madi": {
      "version": "4.5.4",
      "resolved": "https://registry.npmjs.org/@fontsource/ms-madi/-/ms-madi-4.5.4.tgz"
    },
    "@mui/icons-material": {
      "version": "5.10.3",
      "resolved": "https://registry.npmjs.org/@mui/icons-material/-/icons-material-5.10.3.tgz"
    },
    "@mui/material": {
      "version": "5.10.3",
      "resolved": "https://registry.npmjs.org/@mui/material/-/material-5.10.3.tgz"
    },
    "@testing-library/jest-dom": {
      "version": "5.16.5",
      "resolved": "https://registry.npmjs.org/@testing-library/jest-dom/-/jest-dom-5.16.5.tgz"
    },
    "@testing-library/react": {
      "version": "13.3.0",
      "resolved": "https://registry.npmjs.org/@testing-library/react/-/react-13.3.0.tgz"
    },
    "@testing-library/user-event": {
      "version": "13.5.0",
      "resolved": "https://registry.npmjs.org/@testing-library/user-event/-/user-event-13.5.0.tgz"
    },
    "react-dom": {
      "version": "18.2.0",
      "resolved": "https://registry.npmjs.org/react-dom/-/react-dom-18.2.0.tgz"
    },
    "react-scripts": {
      "version": "5.0.1",
      "resolved": "https://registry.npmjs.org/react-scripts/-/react-scripts-5.0.1.tgz"
    },
    "react-typewriter-effect": {
      "version": "1.1.0",
      "resolved": "https://registry.npmjs.org/react-typewriter-effect/-/react-typewriter-effect-1.1.0.tgz"
    },
    "react": {
      "version": "18.2.0",
      "resolved": "https://registry.npmjs.org/react/-/react-18.2.0.tgz"
    },
    "typewriter-effect": {
      "version": "2.19.0",
      "resolved": "https://registry.npmjs.org/typewriter-effect/-/typewriter-effect-2.19.0.tgz"
    },
    "web-vitals": {
      "version": "2.1.4",
      "resolved": "https://registry.npmjs.org/web-vitals/-/web-vitals-2.1.4.tgz"
    }
  }
}
